setup.cfg
setup.py
tellmewhen.egg-info/PKG-INFO
tellmewhen.egg-info/SOURCES.txt
tellmewhen.egg-info/dependency_links.txt
tellmewhen.egg-info/entry_points.txt
tellmewhen.egg-info/requires.txt
tellmewhen.egg-info/top_level.txt
tmw/__init__.py
tmw/cli.py
tmw/config.py
tmw/core.py
tmw/notify.py
tmw/server.py
tmw/static/css/bootstrap-responsive.css
tmw/static/css/bootstrap-responsive.min.css
tmw/static/css/bootstrap.css
tmw/static/css/bootstrap.min.css
tmw/static/css/font-awesome.css
tmw/static/css/font-awesome.min.css
tmw/static/css/style.css
tmw/static/fonts/FontAwesome.otf
tmw/static/fonts/fontawesome-webfont.eot
tmw/static/fonts/fontawesome-webfont.svg
tmw/static/fonts/fontawesome-webfont.ttf
tmw/static/fonts/fontawesome-webfont.woff
tmw/static/fonts/fontawesome-webfont.woff2
tmw/static/img/favicon.ico
tmw/static/img/glyphicons-halflings-white.png
tmw/static/img/glyphicons-halflings.png
tmw/static/img/ht7.png
tmw/static/img/logo.png
tmw/static/img/readme-logo.png
tmw/static/js/base.js
tmw/static/js/bootstrap.js
tmw/static/js/bootstrap.min.js
tmw/static/js/jquery-2.1.3.min.js
tmw/templates/archive-year.html
tmw/templates/archive.html
tmw/templates/base.html
tmw/templates/builder.html
tmw/templates/email-notification.html
tmw/templates/hello.html
tmw/templates/index.html
tmw/templates/settings.html