Metadata-Version: 1.0
Name: tellmewhen
Version: 0.3
Summary: A simple tool to watch web resources and notify you when they change.
Home-page: http://cpenner461.github.io/tellmewhen/
Author: Charlie Penner
Author-email: charles.penner@gmail.com
License: UNKNOWN
Platform: UNKNOWN
